polylidar_pybind.cpython-310-x86_64-linux-gnu.so
polylidar.libs/libgomp-a34b3233.so.1.0.0
polylidar/__init__.py
polylidar/__main__.py
polylidar/polylidarutil/plane_filtering.py
polylidar/polylidarutil/descartes_patch.py
polylidar/polylidarutil/line_mesh.py
polylidar/polylidarutil/open3d_util.py
polylidar/polylidarutil/__init__.py
polylidar-1.0.9.dist-info/RECORD
polylidar-1.0.9.dist-info/LICENSE
polylidar-1.0.9.dist-info/WHEEL
polylidar-1.0.9.dist-info/METADATA
polylidar-1.0.9.dist-info/top_level.txt
