Metadata-Version: 2.1
Name: polylidar
Version: 1.0.9
Summary: Polygon extracton from 3D Data
Home-page: https://github.com/JeremyBYU/polylidar
Author: Jeremy Castagno
Author-email: jeremybyu@gmail.com
License: MIT
License-File: LICENSE
Requires-Dist: numpy (>=1.15.0)
Requires-Dist: shapely
Requires-Dist: matplotlib
